{"minVersion":"0.1","headerImage":"https://codeymoore.github.io/repo/assets/com.codeymoore.cpuxcrack/banner.png","tintColor":"#FF000","tabs":[{"tabname":"Details","views":[{"class":"HiddenDepictionScreenshotsView","screenshots":[],"itemCornerRadius":8,"itemSize":false},{"markdown":"### Premium for CPU-X app!\n\nSupports armv7 armv7s arm64 and arm64e architectures\nShould work on iOS 8.0-14.5 (only tested on iOS 13.5 and 14.3)\n\nNo options to enable. Just install and enjoy.\n\nGives CPU-X app users premium features.\n\n","useSpacing":"true","class":"DepictionMarkdownView"},{"class":"DepictionSpacerView"},{"class":"DepictionHeaderView","title":"Information"},{"class":"DepictionTableTextView","title":"Developer","text":"Codey Moore"},{"class":"DepictionTableTextView","title":"Version","text":"1.1"},{"class":"DepictionTableTextView","title":"Compatibility","text":"iOS 8.0.0 to 14.5"},{"class":"DepictionTableTextView","title":"Section","text":"Tweaks"},{"class":"DepictionSpacerView"},{"class":"DepictionTableButtonView","title":"Contact Support","action":"depiction-https://codeymoore.github.io/repo/depiction/native/help/com.codeymoore.cpuxcrack.json","openExternal":"true","tintColor":"#FF000"},{"class":"DepictionLabelView","text":" 14/02/17 ","textColor":"#999999","fontSize":"10.0","alignment":1}],"class":"DepictionStackView"},{"tabname":"Changelog","views":[{"class":"DepictionMarkdownView","markdown":"#### Version 1.1\n\nAdded proper support for arm64e."},{"class":"DepictionMarkdownView","markdown":"#### Version 1.0\n\nInitial Release."},{"class":"DepictionLabelView","text":" 14/02/17 ","textColor":"#999999","fontSize":"10.0","alignment":1}],"class":"DepictionStackView"}],"class":"DepictionTabView"}